evewiki/__init__.py
evewiki/admin.py
evewiki/app_settings.py
evewiki/apps.py
evewiki/auth_hooks.py
evewiki/forms.py
evewiki/tasks.py
evewiki/urls.py
evewiki/views.py
evewiki/migrations/0001_initial.py
evewiki/migrations/__init__.py
evewiki/models/__init__.py
evewiki/models/logs.py
evewiki/models/page_versions.py
evewiki/models/pages.py
evewiki/models/settings.py
evewiki/templates/evewiki/base.html
evewiki/templates/evewiki/help.html
evewiki/templates/evewiki/index.html
evewiki/templates/evewiki/page.html
evewiki/templates/evewiki/page_delete.html
evewiki/templates/evewiki/page_tree.html
evewiki/templates/evewiki/sidebar.html
evewiki/tests/__init__.py
evewiki/tests/test_tasks.py
evewiki-0.1.1.dist-info/licenses/LICENSE
evewiki-0.1.1.dist-info/WHEEL
evewiki-0.1.1.dist-info/METADATA
evewiki-0.1.1.dist-info/RECORD
