Metadata-Version: 2.4
Name: evewiki
Version: 0.1.1
Summary: Wiki plugin app for Alliance Auth.
Author-email: Ryan Cunning <ryan.cunning@gmail.com>
Requires-Python: >=3.8
Classifier: Environment :: Web Environment
Classifier: Framework :: Django
Classifier: Framework :: Django :: 4.0
Classifier: Framework :: Django :: 4.2
Classifier: Intended Audience :: Developers
Classifier: License :: OSI Approved :: MIT License
Classifier: Operating System :: OS Independent
Classifier: Programming Language :: Python
Classifier: Programming Language :: Python :: 3.8
Classifier: Programming Language :: Python :: 3.9
Classifier: Programming Language :: Python :: 3.10
Classifier: Programming Language :: Python :: 3.11
Classifier: Topic :: Internet :: WWW/HTTP
Classifier: Topic :: Internet :: WWW/HTTP :: Dynamic Content
License-File: LICENSE
Requires-Dist: allianceauth>=3
Project-URL: Changelog, https://gitlab.com/cunningdesigns/aa-wiki/-/blob/main/CHANGELOG.md
Project-URL: Documentation, https://gitlab.com/cunningdesigns/aa-wiki
Project-URL: Homepage, https://gitlab.com/cunningdesigns/aa-wiki
Project-URL: Source, https://gitlab.com/cunningdesigns/aa-wiki
Project-URL: Tracker, https://gitlab.com/cunningdesigns/aa-wiki/-/issues
